lexapi/__init__.py
lexapi/lex-api.org
lexapi/lexapi.py
lexapi/lextypes.py
lexapi-0.0.1.dist-info/LICENSE
lexapi-0.0.1.dist-info/METADATA
lexapi-0.0.1.dist-info/WHEEL
lexapi-0.0.1.dist-info/top_level.txt
lexapi-0.0.1.dist-info/RECORD
