Metadata-Version: 2.1
Name: lexapi
Version: 0.0.1
Summary: An API for the Lex app
Home-page: https://gitlab.com/finnoleary/lexapi
Author: Alex O'Leary
Author-email: alexandria@inventati.org
License: UNKNOWN
Platform: UNKNOWN
Classifier: Topic :: Software Development :: Libraries
Classifier: Programming Language :: Python :: 3
Classifier: License :: OSI Approved :: MIT License
Classifier: Operating System :: OS Independent
Requires-Python: >=3.8
Requires-Dist: requests (>=2.22.0)
Requires-Dist: pure-protobuf (>=2.0.0)
